alibabacloud_esa20240910/__init__.py
alibabacloud_esa20240910/client.py
alibabacloud_esa20240910/models/__init__.py
alibabacloud_esa20240910/models/_activate_client_certificate_request.py
alibabacloud_esa20240910/models/_activate_client_certificate_response.py
alibabacloud_esa20240910/models/_activate_client_certificate_response_body.py
alibabacloud_esa20240910/models/_activate_version_management_request.py
alibabacloud_esa20240910/models/_activate_version_management_response.py
alibabacloud_esa20240910/models/_activate_version_management_response_body.py
alibabacloud_esa20240910/models/_apply_certificate_request.py
alibabacloud_esa20240910/models/_apply_certificate_response.py
alibabacloud_esa20240910/models/_apply_certificate_response_body.py
alibabacloud_esa20240910/models/_apply_custom_hostname_certificate_request.py
alibabacloud_esa20240910/models/_apply_custom_hostname_certificate_response.py
alibabacloud_esa20240910/models/_apply_custom_hostname_certificate_response_body.py
alibabacloud_esa20240910/models/_batch_create_records_request.py
alibabacloud_esa20240910/models/_batch_create_records_response.py
alibabacloud_esa20240910/models/_batch_create_records_response_body.py
alibabacloud_esa20240910/models/_batch_create_records_shrink_request.py
alibabacloud_esa20240910/models/_batch_create_waf_rules_request.py
alibabacloud_esa20240910/models/_batch_create_waf_rules_response.py
alibabacloud_esa20240910/models/_batch_create_waf_rules_response_body.py
alibabacloud_esa20240910/models/_batch_create_waf_rules_shrink_request.py
alibabacloud_esa20240910/models/_batch_delete_kv_request.py
alibabacloud_esa20240910/models/_batch_delete_kv_response.py
alibabacloud_esa20240910/models/_batch_delete_kv_response_body.py
alibabacloud_esa20240910/models/_batch_delete_kv_shrink_request.py
alibabacloud_esa20240910/models/_batch_delete_kv_with_high_capacity_advance_request.py
alibabacloud_esa20240910/models/_batch_delete_kv_with_high_capacity_request.py
alibabacloud_esa20240910-2.37.0.dist-info/LICENSE
alibabacloud_esa20240910-2.37.0.dist-info/METADATA
alibabacloud_esa20240910-2.37.0.dist-info/WHEEL
alibabacloud_esa20240910-2.37.0.dist-info/top_level.txt
alibabacloud_esa20240910-2.37.0.dist-info/RECORD
